Metadata-Version: 1.1
Name: kafka-scrapy
Version: 0.4.37
Summary: kafka-based components for Scrapy.
Home-page: https://github.com/kwx1996/kafka_scrapy
Author: kong
Author-email: tomngp@163.com
License: UNKNOWN
Download-URL: https://github.com/kwx1996/kafka_scrapy/archive/master.zip
Platform: UNKNOWN
